AUTHORS
LICENSE
MANIFEST.in
README.rst
setup.py
django_request_log.egg-info/PKG-INFO
django_request_log.egg-info/SOURCES.txt
django_request_log.egg-info/dependency_links.txt
django_request_log.egg-info/not-zip-safe
django_request_log.egg-info/top_level.txt
log/__init__.py
log/admin.py
log/middleware.py
log/models.py
log/migrations/0001_initial.py
log/migrations/__init__.py
log/south_migrations/0001_initial.py
log/south_migrations/__init__.py
requirements/dev.txt
requirements/test.txt